conllup/__init__.py
conllup/conllup.py
conllup/processing.py
conllup/types.py
conllup-3.1.1.dist-info/METADATA
conllup-3.1.1.dist-info/WHEEL
conllup-3.1.1.dist-info/top_level.txt
conllup-3.1.1.dist-info/RECORD
