Metadata-Version: 2.1
Name: conllup
Version: 3.1.1
Summary: Convert CONLLU to/from JSON format
Author: Kirian GUILLER
Author-email: kirianguiller@gmail.com
License: MIT
Keywords: CONLLU,JSON,arborator
Classifier: Programming Language :: Python :: 3
Requires-Python: >=3.8
